{"college":"gies_college_of_business","slides":[{"data":"","filename":"/images/gies3019/social_media.jpg","filenameCompressed":"https://digitalsign2.education.illinois.edu/images_web/gies3019/social_media.jpg","filenameFull":"https://digitalsign2.education.illinois.edu/images/gies3019/social_media.jpg","title":"Social_Media.jpg","type":"image"},{"data":"","filename":"/images/gies3019/careerfair.jpg","filenameCompressed":"https://digitalsign.itpartners.illinois.edu/images_web/gies3019/careerfair.jpg","filenameFull":"https://digitalsign.itpartners.illinois.edu/images/gies3019/careerfair.jpg","title":"CareerFair.jpg","type":"image"},{"data":"","filename":"/images/gies3019/vbb_student_consultant.jpg","filenameCompressed":"https://digitalsign2.education.illinois.edu/images_web/gies3019/vbb_student_consultant.jpg","filenameFull":"https://digitalsign2.education.illinois.edu/images/gies3019/vbb_student_consultant.jpg","title":"VBB_Student_Consultant.jpg","type":"image"},{"data":"","filename":"/images/gies3019/giessocialmediavbb.jpg","filenameCompressed":"https://digitalsign.itpartners.illinois.edu/images_web/gies3019/giessocialmediavbb.jpg","filenameFull":"https://digitalsign.itpartners.illinois.edu/images/gies3019/giessocialmediavbb.jpg","title":"giessocialmediavbb.jpg","type":"image"},{"data":"","filename":"/images/gies3019/forbes12.jpg","filenameCompressed":"https://digitalsign.itpartners.illinois.edu/images_web/gies3019/forbes12.jpg","filenameFull":"https://digitalsign.itpartners.illinois.edu/images/gies3019/forbes12.jpg","title":"Forbes12.jpg","type":"image"},{"data":"","filename":"/images/gies3019/latinx_heritage_monthvbbopt2.jpg","filenameCompressed":"https://digitalsign.itpartners.illinois.edu/images_web/gies3019/latinx_heritage_monthvbbopt2.jpg","filenameFull":"https://digitalsign.itpartners.illinois.edu/images/gies3019/latinx_heritage_monthvbbopt2.jpg","title":"Latinx_Heritage_MonthVBBOpt2.jpg","type":"image"},{"data":"","filename":"/images/gies3019/flu_shot_clinic_vbb__option_3.jpg","filenameCompressed":"https://digitalsign.itpartners.illinois.edu/images_web/gies3019/flu_shot_clinic_vbb__option_3.jpg","filenameFull":"https://digitalsign.itpartners.illinois.edu/images/gies3019/flu_shot_clinic_vbb__option_3.jpg","title":"Flu_Shot_Clinic_VBB__Option_3.jpg","type":"image"},{"data":"","filename":"/images/gies3019/fall_festivalvbb03.jpg","filenameCompressed":"https://digitalsign.itpartners.illinois.edu/images_web/gies3019/fall_festivalvbb03.jpg","filenameFull":"https://digitalsign.itpartners.illinois.edu/images/gies3019/fall_festivalvbb03.jpg","title":"Fall_FestivalVBB03.jpg","type":"image"}],"title":"BIF 3019 – Graduate Programs","twitter":"","url":"gies3019"}